torch_struct/__init__.py
torch_struct/alignment.py
torch_struct/autoregressive.py
torch_struct/cky.py
torch_struct/cky_crf.py
torch_struct/deptree.py
torch_struct/distributions.py
torch_struct/helpers.py
torch_struct/linearchain.py
torch_struct/semimarkov.py
torch_struct/test_algorithms.py
torch_struct/semirings/__init__.py
torch_struct/semirings/checkpoint.py
torch_struct/semirings/fast_semirings.py
torch_struct/semirings/sample.py
torch_struct/semirings/semirings.py
torch_struct/semirings/sparse_max.py
torch_struct-0.5.dist-info/LICENSE
torch_struct-0.5.dist-info/METADATA
torch_struct-0.5.dist-info/WHEEL
torch_struct-0.5.dist-info/top_level.txt
torch_struct-0.5.dist-info/RECORD
