Metadata-Version: 2.1
Name: torch-struct
Version: 0.5
Summary: UNKNOWN
Home-page: https://github.com/harvardnlp/pytorch-struct
Author: Alexander Rush
Author-email: arush@cornell.edu
License: UNKNOWN
Platform: UNKNOWN
Requires-Python: >=3.6
Requires-Dist: torch
